MANIFEST.in
README.md
setup.py
liver/__init__.py
liver/admin.py
liver/forms.py
liver/models.py
liver/tests.py
liver/urls.py
liver/utils.py
liver/views.py
liver.egg-info/PKG-INFO
liver.egg-info/SOURCES.txt
liver.egg-info/dependency_links.txt
liver.egg-info/not-zip-safe
liver.egg-info/requires.txt
liver.egg-info/top_level.txt
liver/migrations/0001_initial.py
liver/migrations/0002_auto__add_application.py
liver/migrations/0003_auto__chg_field_recordingjob_result__chg_field_recordingsource_sources.py
liver/migrations/__init__.py
liver/static/liver/jwplayer_6_11/README.html
liver/static/liver/jwplayer_6_11/jwplayer.flash.swf
liver/static/liver/jwplayer_6_11/jwplayer.html5.js
liver/static/liver/jwplayer_6_11/jwplayer.js
liver/templates/admin/liver/import_action.html
liver/templates/admin/liver/recording/change_form.html
liver/templates/admin/liver/recording/player.html
tools/
tools/liver-delete-jobs
tools/liver-delete-recordings
tools/liver-do-jobs
tools/liver-get-mo-to-delete
tools/liver-mo-status