Metadata-Version: 1.1
Name: liver
Version: 0.5.4
Summary: Video recorder
Home-page: http://github.com/psaavedra/liver
Author: Pablo Saavedra
Author-email: pablo.saavedra@interoud.com
License: Copyright (R) - 2014 Interoud
